{
"type": "FeatureCollection",
"name": "parada1",
"crs": { "type": "name", "properties": { "name": "urn:ogc:def:crs:OGC:1.3:CRS84" } },
"features": [
{ "type": "Feature", "properties": { "Parada 1": "Plaza del Mercado" }, "geometry": { "type": "Point", "coordinates": [ -2.4460374, 42.4667716 ] } }
]
}
