{
"type": "FeatureCollection",
"name": "parada4",
"crs": { "type": "name", "properties": { "name": "urn:ogc:def:crs:OGC:1.3:CRS84" } },
"features": [
{ "type": "Feature", "properties": { "Parada 4": "Calle García Morato" }, "geometry": { "type": "Point", "coordinates": [ -2.44743878, 42.4621707 ] } }
]
}
